LICENSE
README.md
setup.py
AllWhatsPy/__init__.py
AllWhatsPy/audio_awp.py
AllWhatsPy/business_awp.py
AllWhatsPy/contatos_awp.py
AllWhatsPy/criptografia_awp.py
AllWhatsPy/decorators_awp.py
AllWhatsPy/errors_awp.py
AllWhatsPy/main.py
AllWhatsPy/mensagem_awp.py
AllWhatsPy/utilidades_awp.py
allwhatspy_awp.egg-info/PKG-INFO
allwhatspy_awp.egg-info/SOURCES.txt
allwhatspy_awp.egg-info/dependency_links.txt
allwhatspy_awp.egg-info/requires.txt
allwhatspy_awp.egg-info/top_level.txt