Metadata-Version: 2.1
Name: allwhatspy-awp
Version: 0.2.0.9
Summary: Whatsapp Wrapper - Envio de Mensagem Automática - PT-BR. 
Author: Lucas Lourenço
Author-email: dev.lucaslourenco@gmail.com
License: MIT License
Keywords: whatsapp api bot mensagem automática analise whatsappAPI allwhatspy awp allwhatspy-awp wrapper message contact analysis github automação automacao
License-File: LICENSE
